{
    "addressComponents": [
        {
            "languageCode": "fa",
            "longText": "استان تهران، تهران، فلکه دوم صادقیه،خیابان ایت ا..کاشانی،جنب، خیابان مهران،"
        },
        {
            "languageCode": "en-US",
            "longText": "P8GC+WJC",
            "shortText": "P8GC+WJC",
            "types": [
                "plus_code"
            ]
        },
        {
            "languageCode": "en",
            "longText": "Tehran",
            "shortText": "Tehran",
            "types": [
                "locality",
                "political"
            ]
        },
        {
            "languageCode": "en",
            "longText": "Tehran",
            "shortText": "Tehran",
            "types": [
                "administrative_area_level_2",
                "political"
            ]
        },
        {
            "languageCode": "en",
            "longText": "Iran",
            "shortText": "IR",
            "types": [
                "country",
                "political"
            ]
        }
    ],
    "addressDescriptor": {
        "areas": [
            {
                "containment": "OUTSKIRTS",
                "displayName": {
                    "languageCode": "en",
                    "text": "Mehran"
                },
                "name": "places/ChIJ-6R9JKT9jT8R2cfeUcr3-OM",
                "placeId": "ChIJ-6R9JKT9jT8R2cfeUcr3-OM"
            },
            {
                "containment": "OUTSKIRTS",
                "displayName": {
                    "languageCode": "en",
                    "text": "Ferdows"
                },
                "name": "places/ChIJQ-413779jT8R7lWt_dHTS7s",
                "placeId": "ChIJQ-413779jT8R7lWt_dHTS7s"
            },
            {
                "containment": "WITHIN",
                "displayName": {
                    "languageCode": "en",
                    "text": "District 5"
                },
                "name": "places/ChIJj6MsOh79jT8R4iZ5d5Vukqk",
                "placeId": "ChIJj6MsOh79jT8R4iZ5d5Vukqk"
            }
        ],
        "landmarks": [
            {
                "displayName": {
                    "languageCode": "en",
                    "text": "Sina Bank"
                },
                "name": "places/ChIJi3TAUbz9jT8R3I1fqDDGro0",
                "placeId": "ChIJi3TAUbz9jT8R3I1fqDDGro0",
                "spatialRelationship": "DOWN_THE_ROAD",
                "straightLineDistanceMeters": 140.53595,
                "travelDistanceMeters": 140.03386,
                "types": [
                    "bank",
                    "establishment",
                    "finance",
                    "point_of_interest"
                ]
            },
            {
                "displayName": {
                    "languageCode": "en",
                    "text": "Dr. Khorsand 24-hour Pharmacy"
                },
                "name": "places/ChIJ5-Q5W7z9jT8R_UnEJiyLdxY",
                "placeId": "ChIJ5-Q5W7z9jT8R_UnEJiyLdxY",
                "spatialRelationship": "DOWN_THE_ROAD",
                "straightLineDistanceMeters": 147.26128,
                "travelDistanceMeters": 326.15756,
                "types": [
                    "establishment",
                    "health",
                    "pharmacy",
                    "point_of_interest",
                    "store"
                ]
            },
            {
                "displayName": {
                    "languageCode": "fa",
                    "text": "دوچرخه اسکوتر ماشین شارژی کیسان"
                },
                "name": "places/ChIJOwCPBy79jT8RsljkwvcKgOI",
                "placeId": "ChIJOwCPBy79jT8RsljkwvcKgOI",
                "straightLineDistanceMeters": 43.667774,
                "travelDistanceMeters": 200.9274,
                "types": [
                    "bicycle_store",
                    "establishment",
                    "point_of_interest",
                    "store"
                ]
            },
            {
                "displayName": {
                    "languageCode": "en",
                    "text": "Mehran Station"
                },
                "name": "places/ChIJA47VtL39jT8R_BhTfaGF6rc",
                "placeId": "ChIJA47VtL39jT8R_BhTfaGF6rc",
                "straightLineDistanceMeters": 108.08283,
                "travelDistanceMeters": 164.77362,
                "types": [
                    "bus_station",
                    "establishment",
                    "point_of_interest",
                    "transit_station"
                ]
            },
            {
                "displayName": {
                    "languageCode": "en",
                    "text": "Bank Day"
                },
                "name": "places/ChIJVTJFYrv9jT8RftXj_kYKHRw",
                "placeId": "ChIJVTJFYrv9jT8RftXj_kYKHRw",
                "straightLineDistanceMeters": 65.515205,
                "travelDistanceMeters": 182.09892,
                "types": [
                    "bank",
                    "establishment",
                    "finance",
                    "point_of_interest"
                ]
            }
        ]
    },
    "businessStatus": "CLOSED_TEMPORARILY",
    "displayName": {
        "languageCode": "en",
        "text": "Kaban Hall Complex"
    },
    "formattedAddress": "Tehran, استان تهران، تهران، فلکه دوم صادقیه،خیابان ایت ا..کاشانی،جنب، خیابان مهران،، P8GC+WJC, Iran",
    "googleMapsLinks": {
        "directionsUri": "https://www.google.com/maps/dir//''/data=!4m7!4m6!1m1!4e2!1m2!1m1!1s0x3f8dfd6554ae6111:0xba867031ff57b33!3e0?g_mp=Cilnb29nbGUubWFwcy5wbGFjZXMudjEuUGxhY2VzLlNlYXJjaE5lYXJieRACGAEgAA",
        "photosUri": "https://www.google.com/maps/place//data=!4m3!3m2!1s0x3f8dfd6554ae6111:0xba867031ff57b33!10e5?g_mp=Cilnb29nbGUubWFwcy5wbGFjZXMudjEuUGxhY2VzLlNlYXJjaE5lYXJieRACGAEgAA",
        "placeUri": "https://maps.google.com/?cid=840034593623341875&g_mp=Cilnb29nbGUubWFwcy5wbGFjZXMudjEuUGxhY2VzLlNlYXJjaE5lYXJieRACGAEgAA",
        "reviewsUri": "https://www.google.com/maps/place//data=!4m4!3m3!1s0x3f8dfd6554ae6111:0xba867031ff57b33!9m1!1b1?g_mp=Cilnb29nbGUubWFwcy5wbGFjZXMudjEuUGxhY2VzLlNlYXJjaE5lYXJieRACGAEgAA",
        "writeAReviewUri": "https://www.google.com/maps/place//data=!4m3!3m2!1s0x3f8dfd6554ae6111:0xba867031ff57b33!12e1?g_mp=Cilnb29nbGUubWFwcy5wbGFjZXMudjEuUGxhY2VzLlNlYXJjaE5lYXJieRACGAEgAA"
    },
    "googleMapsUri": "https://maps.google.com/?cid=840034593623341875&g_mp=Cilnb29nbGUubWFwcy5wbGFjZXMudjEuUGxhY2VzLlNlYXJjaE5lYXJieRACGAEgAA",
    "iconBackgroundColor": "#FF9E67",
    "iconMaskBaseUri": "https://maps.gstatic.com/mapfiles/place_api/icons/v2/restaurant_pinlet",
    "id": "ChIJEWGuVGX9jT8RM3v1HwNnqAs",
    "internationalPhoneNumber": "+98 912 666 1266",
    "location": {
        "latitude": 35.7273188,
        "longitude": 51.321521999999995
    },
    "name": "places/ChIJEWGuVGX9jT8RM3v1HwNnqAs",
    "nationalPhoneNumber": "0912 666 1266",
    "photos": [
        {
            "authorAttributions": [
                {
                    "displayName": "اللهم عجل لولیک الفرج",
                    "photoUri": "https://lh3.googleusercontent.com/a-/ALV-UjUk0U1Lj68s4a34JsDO3NtcBZsCqpG08K5v2hbUZXbPqiJP7Z4=s100-p-k-no-mo",
                    "uri": "https://maps.google.com/maps/contrib/110270054442916889102"
                }
            ],
            "flagContentUri": "https://www.google.com/local/imagery/report/?cb_client=maps_api_places.places_api&image_key=!1e10!2sCIHM0ogKEICAgICEhYaJygE&hl=en-US",
            "googleMapsUri": "https://www.google.com/maps/place//data=!3m4!1e2!3m2!1sCIHM0ogKEICAgICEhYaJygE!2e10!4m2!3m1!1s0x3f8dfd6554ae6111:0xba867031ff57b33",
            "heightPx": 1536,
            "name": "places/ChIJEWGuVGX9jT8RM3v1HwNnqAs/photos/AZLasHqmaYUiZJ7bCz7i-cecOxjj7v4-wYt5qzsYZCpmBatfg-jobcL0YrrWyTx125R8EyzWsiSn4un1_cNqdMhRq5kcIwoo1NxSGjmZKa-yOA8zCDpf8Yk6-pxcb4Rg8iMSATAjU2ppn8kw5BSMr4Vb7DeWkBb6TiEM68I_mBIM6ytX876dFyZX3-kL85w--VQyAXbLbbq_EV2tqiWepE1-CvmX0Cg-zapzRYVKd1dXvn01xvh-EiGC55qhqIr2kv4uIgAFlOubhkNNnPvQ_tK_bJ5iI7A-pOBx2wUOD0xhVwF-f1-mURo8poqHG1KWO8W0KTROJEdkyJMbMZRIlOvDgZFO2xmGp1NnjgzaNz9mJVr1nUa-3BFf3Jsqf378-AupGQogrgt77V1apQooI-K8rLelFUM36vaduvuZUqyHfKFCmMYO",
            "widthPx": 2048
        },
        {
            "authorAttributions": [
                {
                    "displayName": "اللهم عجل لولیک الفرج",
                    "photoUri": "https://lh3.googleusercontent.com/a-/ALV-UjUk0U1Lj68s4a34JsDO3NtcBZsCqpG08K5v2hbUZXbPqiJP7Z4=s100-p-k-no-mo",
                    "uri": "https://maps.google.com/maps/contrib/110270054442916889102"
                }
            ],
            "flagContentUri": "https://www.google.com/local/imagery/report/?cb_client=maps_api_places.places_api&image_key=!1e10!2sCIHM0ogKEICAgICEhe2sNQ&hl=en-US",
            "googleMapsUri": "https://www.google.com/maps/place//data=!3m4!1e2!3m2!1sCIHM0ogKEICAgICEhe2sNQ!2e10!4m2!3m1!1s0x3f8dfd6554ae6111:0xba867031ff57b33",
            "heightPx": 1536,
            "name": "places/ChIJEWGuVGX9jT8RM3v1HwNnqAs/photos/AZLasHq5DW35V59LKrbASek9aRqrUFlnwsr_R_uJbrdRy473Ocy99EH9tP12NZdXmDhB30UzQCOg9gbVRbdp01wBr3EISJmfySL1waiuscVS8PULg0Dv_BnOj7Damb5M6pnQhwuJC3uBrQ3vH-0v1QJdpYlZ9ZfOFYo3FZ1_mRqXRTPZvLscJDf7F8KyZnFu7p2g1PwsBxezFBkHDWCjA2r4fSzb5DpGW1NhIczyXffINkAIQFONZgZMYZpXR0P8K-R7I3EYkuFWxtyHzO5ap9MyRaeZ7CZlVnetm8fG46dyoesVwJssHqE9pkP9l9UpBMd9yXSrzWaWl-9qJQ5yuIw3runuJrF-eiD7LA8s8YVilu5q3VPnUAMFwSkN3DIL5MEUuvBNxkGxy0Sx3zTnrOa_EfJmbbNAKmZjctmRiUPUOM3oGA",
            "widthPx": 2048
        },
        {
            "authorAttributions": [
                {
                    "displayName": "Reza Karami",
                    "photoUri": "https://lh3.googleusercontent.com/a-/ALV-UjUZ1pe5z1qDSB8nGw_lGuyWLBQkwYtIQ2_xxyjgoeTXf_zEWoZJ=s100-p-k-no-mo",
                    "uri": "https://maps.google.com/maps/contrib/111862610430223597181"
                }
            ],
            "flagContentUri": "https://www.google.com/local/imagery/report/?cb_client=maps_api_places.places_api&image_key=!1e10!2sCIHM0ogKEICAgIClm960BQ&hl=en-US",
            "googleMapsUri": "https://www.google.com/maps/place//data=!3m4!1e2!3m2!1sCIHM0ogKEICAgIClm960BQ!2e10!4m2!3m1!1s0x3f8dfd6554ae6111:0xba867031ff57b33",
            "heightPx": 1440,
            "name": "places/ChIJEWGuVGX9jT8RM3v1HwNnqAs/photos/AZLasHp_HCn9EZ-wuRj_ig_p8IHJns2t2fOIcbb4oEwL82scvq895SJdBJYiuypPttfcmqj5o18UnnyrIj3AvF8t6efklXea9olo_FNdkxj7nmRA63XNujcORTrzGDYiMggaBKzQE986N_ZOEy-fMFAgJmTClSsHVSnlvHtvIeQq0LV-e2_8R38XQNJ_BVk_Gq1C5BLahLUVCfDV8ILr4DFihgDm_ZciC6NMTyoRh7UBF1S_siV88oUoWOK5RoCOT7qgDcscSu5oPxVE-TMQ68wG9ZiBKgKmvrDbDE_cWDBpiLpcnMWJPvtwlkM4rD8cJDlLy8gWvmFWhDWDOfIAjrf13MhDQoH-B7WB16yIV6hSjEmHxB5wo_qSIHhAZdtBafk-qokB6zjtp25hlwq6HqEcxT9JDxm2TyG4Bb9ElRQcQkg",
            "widthPx": 1080
        },
        {
            "authorAttributions": [
                {
                    "displayName": "Alireza Fathi",
                    "photoUri": "https://lh3.googleusercontent.com/a-/ALV-UjWCJvvYglVkIRLQBwY2tyr3TPdUzSo_ZoxUIReW3gyYU4pEO5Dw=s100-p-k-no-mo",
                    "uri": "https://maps.google.com/maps/contrib/108885426467965453555"
                }
            ],
            "flagContentUri": "https://www.google.com/local/imagery/report/?cb_client=maps_api_places.places_api&image_key=!1e10!2sCIHM0ogKEICAgIDktf-9fg&hl=en-US",
            "googleMapsUri": "https://www.google.com/maps/place//data=!3m4!1e2!3m2!1sCIHM0ogKEICAgIDktf-9fg!2e10!4m2!3m1!1s0x3f8dfd6554ae6111:0xba867031ff57b33",
            "heightPx": 3968,
            "name": "places/ChIJEWGuVGX9jT8RM3v1HwNnqAs/photos/AZLasHrZF-gf2IHTOKLcMQNkM-ia1UwsxViccB-uZGURPnhwCjBsg4i8BihXJs2h0utFa5dCeuvbHxP6pzt2UyNLbHXrAj7CbC05Co0hupehFdrWNZR2pb5US2Cg_Dn8iHdnnJ_CBBJvL-yzVsI4A_BWNoJLDQ5dAsDp2ITnu0wlUXIKp0tObq2J3MF7cnYAUR_W5n8BsCaziyWVW_R9o5WWndY7tkPSGq1gVXyr2gobPt_VIGaNgkomYr8er5XQAvHoICAZQH2MReJkHfXq_KFggxDZCTx0OCYD6OFmh0G8ZN2860uM6hhnt6AJGzFx1abFnc3DPCQEwU1L5msS4Xr46i-2fN2i8duYuDWJV5D0nX7EKtGn6kam0VySdSbL9h4ObpzUYcfLGJ0soX7-WIp2KQk8E7U6p-b2i045Cwvqsqp1GQ",
            "widthPx": 2976
        },
        {
            "authorAttributions": [
                {
                    "displayName": "Alireza Safari علیرضا صفری",
                    "photoUri": "https://lh3.googleusercontent.com/a-/ALV-UjVccFNeNbilNgJnIeK4SfzCJX2HOsqFBzWX53rFjekOzHrAByMv=s100-p-k-no-mo",
                    "uri": "https://maps.google.com/maps/contrib/104353795322281628564"
                }
            ],
            "flagContentUri": "https://www.google.com/local/imagery/report/?cb_client=maps_api_places.places_api&image_key=!1e10!2sCIHM0ogKEICAgIDEtPaUWQ&hl=en-US",
            "googleMapsUri": "https://www.google.com/maps/place//data=!3m4!1e2!3m2!1sCIHM0ogKEICAgIDEtPaUWQ!2e10!4m2!3m1!1s0x3f8dfd6554ae6111:0xba867031ff57b33",
            "heightPx": 4032,
            "name": "places/ChIJEWGuVGX9jT8RM3v1HwNnqAs/photos/AZLasHpH--PGXF2gkCLdVTOjiKnOLmuH1n_nAeOEhYR18ERnZHMOp_ILQXMWwgI9lOExQ91g9BitbX6dbEaANTEMV0WEO1KpLSFAONNuek9vvr5W3nsIzGJyxfJdCfqvBGHRvrcdNCO9BZM63rasdadqAalnFV8t4e769vI5-fTjJvt1vZ2-lUCQ8-wTPJ_5OdfQXSOO0Gc5GS4EYjknQx6vwVd2qphtO9tUBeD1pZ-2me8Hmh8Tl9iMOz01dYJHyVE4XIFhjAKoN5DHEc9GWzShd2Wq5A9KJgrYN0dY5kwyDoDf4OQkeokN9lUYs4dhlBcf3daQ6feGr7J7ATy4Py5VShaOcEAtNna3dXC_oI582qlJeokFgIkccFM_0OM8dqS-GIMYNVscEE4G7V6e2vEhMIHELxkr72y7DPZ-1k9qreERiQ",
            "widthPx": 3024
        },
        {
            "authorAttributions": [
                {
                    "displayName": "mahdi pourali",
                    "photoUri": "https://lh3.googleusercontent.com/a-/ALV-UjWo09wPIdo8VWgimRWZdViwla6gcVawn7wmG0OgmrByPNv-SJ_Mkw=s100-p-k-no-mo",
                    "uri": "https://maps.google.com/maps/contrib/110200580221316848185"
                }
            ],
            "flagContentUri": "https://www.google.com/local/imagery/report/?cb_client=maps_api_places.places_api&image_key=!1e10!2sCIHM0ogKEICAgICc05OYNQ&hl=en-US",
            "googleMapsUri": "https://www.google.com/maps/place//data=!3m4!1e2!3m2!1sCIHM0ogKEICAgICc05OYNQ!2e10!4m2!3m1!1s0x3f8dfd6554ae6111:0xba867031ff57b33",
            "heightPx": 1860,
            "name": "places/ChIJEWGuVGX9jT8RM3v1HwNnqAs/photos/AZLasHqh5zR_NcbKJO29i9-IVRkc7vE8xXwd7Vlya93EOZH_jMkTQwv5YWy3OzI183saMsAXflM5Sw2uMvqZexsO4LBHNh-Ou19i8Jox8eZYuGJqcURYFZ1h6r6SWyE2Dlb08_etJV-LaIGIKUSgcW8yRkL5vLrtHME84FwLXzoLiu2u7e7ErGdQaEGAOj8nBohummST5F2sx8rQMLr3alCjuL0ym7Rkl-S-LF19J1TGLL3-XwD9BKkOYMscIig7znb0UQVBNP8pPGiXmI2cxkWIdKRGSZVgGuTGuJxhqdErFKDsssadbm1pZRJbxLAbdmHPzLeIZ29zCUn4g8il5KCDDxMBIOWHs92dyFZHBTmgtszMX8rjNBAxHuEpv-0hvtGjCeR4gG1i3NpH9LKLWE8ApOrLc5zKZBLtp9ajXCuDRGXM3w",
            "widthPx": 4032
        },
        {
            "authorAttributions": [
                {
                    "displayName": "Mehrnaz Arshadi",
                    "photoUri": "https://lh3.googleusercontent.com/a-/ALV-UjUwkQjwnJDvPdjl2z_hsAUSIHS-TjJGexUbhV6UUpYY9L4KCMes=s100-p-k-no-mo",
                    "uri": "https://maps.google.com/maps/contrib/109810542756024537637"
                }
            ],
            "flagContentUri": "https://www.google.com/local/imagery/report/?cb_client=maps_api_places.places_api&image_key=!1e10!2sCIHM0ogKEICAgICs-8uDSw&hl=en-US",
            "googleMapsUri": "https://www.google.com/maps/place//data=!3m4!1e2!3m2!1sCIHM0ogKEICAgICs-8uDSw!2e10!4m2!3m1!1s0x3f8dfd6554ae6111:0xba867031ff57b33",
            "heightPx": 1080,
            "name": "places/ChIJEWGuVGX9jT8RM3v1HwNnqAs/photos/AZLasHoa-B_jcVSqNwNU77YPODCiyu0nswxvqg0fDwe2CLOD66nyJzajgOjCqb1MOICBEIWLeGP6XoBkM3DtyeoiOR-FGZ8d7m5KEjRvKDY6yY-TFghYfDS-qyCmWPSVqMFwSY7t34j-7h-Oa-Xl9j7B1D1nBJMOZ8eMkxcYlzw_iPmNniF5WyY27KPwidTePT3in0WIQxSJ7wEQmTnTjHibfKjK3IAVyzmRDXYPf3Emyam87qFlyWhnzh0qFUeO1xR3NTnuRO4NvEdQfwinl0yBYvsSDrdns7QU4FYagng-mQAehB2zGXje0Ew0cqsLBKdhAWTi1MyQknpKvGBkFTgSuIFZxzdxbkI5JGQj7iY2ExL-Sgu_hqmHV7Tbfllv15pvtTrbFkKHLumbrpWXiIy3IoHkaoitVA3T_TC1_8pIgnY",
            "widthPx": 1080
        },
        {
            "authorAttributions": [
                {
                    "displayName": "mahdi pourali",
                    "photoUri": "https://lh3.googleusercontent.com/a-/ALV-UjWo09wPIdo8VWgimRWZdViwla6gcVawn7wmG0OgmrByPNv-SJ_Mkw=s100-p-k-no-mo",
                    "uri": "https://maps.google.com/maps/contrib/110200580221316848185"
                }
            ],
            "flagContentUri": "https://www.google.com/local/imagery/report/?cb_client=maps_api_places.places_api&image_key=!1e10!2sCIHM0ogKEICAgICcy9ytlgE&hl=en-US",
            "googleMapsUri": "https://www.google.com/maps/place//data=!3m4!1e2!3m2!1sCIHM0ogKEICAgICcy9ytlgE!2e10!4m2!3m1!1s0x3f8dfd6554ae6111:0xba867031ff57b33",
            "heightPx": 1860,
            "name": "places/ChIJEWGuVGX9jT8RM3v1HwNnqAs/photos/AZLasHrTSg7TkpUhQ0u7MvtNgLh6XVLhvxPadeWR1-HLhfu8ieG9HbE36KX-r-aSZ33rU5NHaL8k0n44CAcRSqCaOwFMPLqMyBMcYZkklaVL15RwdI_4aJYEKvnHJOqBcYoNlqdiQcG19bFZT2qSD-qB6rLyX6wCKSGEfEFELUdAIkJKX0tohvKNOss2hKyIdch9Yh-t9yXBALMN15GoRISbnTXa9Y5R-UXHVrTj9ki_9uO4dn8h9mVKqi2YWCf6VUhw6tU84yboVZxgattaGRoYrltCsdmDg8nTmK-JdSYCe9WQdIMrGuvsbbqRypqYQsjP36KkzDUq1ImRVjy98IoHs269_9yVySN4sU96eqAYUOdtkPGstiPv9HImWLatAxLwf5ClkASDvxYVxhZ8GFVbEoWuD-SkR6RnIrr6D7x1bnPJ5JE",
            "widthPx": 4032
        },
        {
            "authorAttributions": [
                {
                    "displayName": "mahdi pourali",
                    "photoUri": "https://lh3.googleusercontent.com/a-/ALV-UjWo09wPIdo8VWgimRWZdViwla6gcVawn7wmG0OgmrByPNv-SJ_Mkw=s100-p-k-no-mo",
                    "uri": "https://maps.google.com/maps/contrib/110200580221316848185"
                }
            ],
            "flagContentUri": "https://www.google.com/local/imagery/report/?cb_client=maps_api_places.places_api&image_key=!1e10!2sCIHM0ogKEICAgICc0-PHLQ&hl=en-US",
            "googleMapsUri": "https://www.google.com/maps/place//data=!3m4!1e2!3m2!1sCIHM0ogKEICAgICc0-PHLQ!2e10!4m2!3m1!1s0x3f8dfd6554ae6111:0xba867031ff57b33",
            "heightPx": 4032,
            "name": "places/ChIJEWGuVGX9jT8RM3v1HwNnqAs/photos/AZLasHpUHG1Rj-6uer9tVZIjIccj9t2d9oFpQls75k5oaMZweMALWllM9XZFNkRgWTbR7ltUdhY3T8KH6h9ytv15GWO3rB6Xlv8m3QbuA3eYjkhruJ4QulZStKZpWy8pwWmcxyWV4laGCVsZV0oXmk0wq9m4kF3dngBFxh9NW0_E-hT_GbHlNWv-qNVvemIAHMPkGEUVKY2CU7wXHKVfV7fh1LFogK8GK2obHYlFWC3oZHAKmXP2ZBELSHS0xG5vaVeA-Q_UItIpsayFPztpTgY3YXo6AV3Wrjp-y_cTor6jof4goOm7GP0LG4af_zSQ9kJmec1l9JDZLKcvpDTycFph7K8clp9sqEEo2qyn1KgHXgWLQ7Ru2196tvL4fmz55ZH2KouMCr085xMK4qQO0I91a9kqcEeeHMJ0-kqYBCiJT38",
            "widthPx": 1860
        },
        {
            "authorAttributions": [
                {
                    "displayName": "mahdi pourali",
                    "photoUri": "https://lh3.googleusercontent.com/a-/ALV-UjWo09wPIdo8VWgimRWZdViwla6gcVawn7wmG0OgmrByPNv-SJ_Mkw=s100-p-k-no-mo",
                    "uri": "https://maps.google.com/maps/contrib/110200580221316848185"
                }
            ],
            "flagContentUri": "https://www.google.com/local/imagery/report/?cb_client=maps_api_places.places_api&image_key=!1e10!2sCIHM0ogKEICAgICc05PIUg&hl=en-US",
            "googleMapsUri": "https://www.google.com/maps/place//data=!3m4!1e2!3m2!1sCIHM0ogKEICAgICc05PIUg!2e10!4m2!3m1!1s0x3f8dfd6554ae6111:0xba867031ff57b33",
            "heightPx": 4032,
            "name": "places/ChIJEWGuVGX9jT8RM3v1HwNnqAs/photos/AZLasHq_VOpDKFG5bFHBiLUp--FoJVFcZDF9mtA04Te4BATDoOd8jEiCxkHAtAOhKIMwTItfCa3g5EPolprmOubE9nHBEcPmZGFsTDpw6svdzWAUKDBCOkMtjBibiN17zs8L9Lp6amTvdwTFPH_-LmJ-WX2i60GheXRuXKfn5Dp5y1hKel2PwhXT0fX6UHKMT84vQbhoa-uoIj9gIx59HcUfkvH2nJKqcxxEnqpBCbFCvXpN8k0H8JCXF4wf3xwYZBA5J2Zabt3HRF6fgJB_ezl1diOz0emk9BnOSpdrton-7Kn6yEh3QlynbWOdICuAk1Y_HvIkBWCGskZ6DVQII0X7PnH5eIU--2eLeblD4wFkhtAcfWBj2uJkjWBg9CDwcdGszs4YfxWEXd3DyXQEmHRSKKsJN4VXndUAVxvTRPx400jZIQ",
            "widthPx": 1860
        }
    ],
    "postalAddress": {
        "addressLines": [
            "استان تهران، تهران، فلکه دوم صادقیه،خیابان ایت ا..کاشانی،جنب، خیابان مهران،",
            "P8GC+WJC"
        ],
        "languageCode": "en-US",
        "locality": "Tehran",
        "regionCode": "IR"
    },
    "primaryType": "restaurant",
    "primaryTypeDisplayName": {
        "languageCode": "en-US",
        "text": "Restaurant"
    },
    "rating": 4.1,
    "reviews": [
        {
            "authorAttribution": {
                "displayName": "cosmic muffin",
                "photoUri": "https://lh3.googleusercontent.com/a-/ALV-UjVwqv1oLAqT7cbjbv1LOJ4dVXhMrmATRvlfdpTHDsPa6nzmWl7VfA=s128-c0x00000000-cc-rp-mo-ba3",
                "uri": "https://www.google.com/maps/contrib/117376186511390568389/reviews"
            },
            "flagContentUri": "https://www.google.com/local/review/rap/report?postId=ChdDSUhNMG9nS0VJQ0FnSURJdWVDYTJBRRAB&d=17924085&t=1",
            "googleMapsUri": "https://www.google.com/maps/reviews/data=!4m6!14m5!1m4!2m3!1sChdDSUhNMG9nS0VJQ0FnSURJdWVDYTJBRRAB!2m1!1s0x3f8dfd6554ae6111:0xba867031ff57b33",
            "name": "places/ChIJEWGuVGX9jT8RM3v1HwNnqAs/reviews/ChdDSUhNMG9nS0VJQ0FnSURJdWVDYTJBRRAB",
            "originalText": {
                "languageCode": "en",
                "text": "Great for photography, one the most high quality building i ever seen"
            },
            "publishTime": "2019-01-12T05:01:22.177374970Z",
            "rating": 5,
            "relativePublishTimeDescription": "6 years ago",
            "text": {
                "languageCode": "en",
                "text": "Great for photography, one the most high quality building i ever seen"
            }
        },
        {
            "authorAttribution": {
                "displayName": "Reza Shabani",
                "photoUri": "https://lh3.googleusercontent.com/a-/ALV-UjVGQzjpiMCWOkpsOdlIPNct7CXXhajSkpCUWKAjfbHtSeepT-o=s128-c0x00000000-cc-rp-mo-ba2",
                "uri": "https://www.google.com/maps/contrib/118142340226425021712/reviews"
            },
            "flagContentUri": "https://www.google.com/local/review/rap/report?postId=ChZDSUhNMG9nS0VJQ0FnSURVbExtclhnEAE&d=17924085&t=1",
            "googleMapsUri": "https://www.google.com/maps/reviews/data=!4m6!14m5!1m4!2m3!1sChZDSUhNMG9nS0VJQ0FnSURVbExtclhnEAE!2m1!1s0x3f8dfd6554ae6111:0xba867031ff57b33",
            "name": "places/ChIJEWGuVGX9jT8RM3v1HwNnqAs/reviews/ChZDSUhNMG9nS0VJQ0FnSURVbExtclhnEAE",
            "originalText": {
                "languageCode": "en",
                "text": "Not bad, a little loud music, ordinary food, parking full, around no park area."
            },
            "publishTime": "2019-08-15T06:25:47.346537Z",
            "rating": 5,
            "relativePublishTimeDescription": "6 years ago",
            "text": {
                "languageCode": "en",
                "text": "Not bad, a little loud music, ordinary food, parking full, around no park area."
            }
        },
        {
            "authorAttribution": {
                "displayName": "Farhad Shiri",
                "photoUri": "https://lh3.googleusercontent.com/a/ACg8ocK4RZlxAyoZJjJFKq0AUax6lkpsja0KOEuI7Qp02t8T-ClAmvYB=s128-c0x00000000-cc-rp-mo-ba3",
                "uri": "https://www.google.com/maps/contrib/117117017196253267184/reviews"
            },
            "flagContentUri": "https://www.google.com/local/review/rap/report?postId=ChZDSUhNMG9nS0VJQ0FnSURNLVptY1FnEAE&d=17924085&t=1",
            "googleMapsUri": "https://www.google.com/maps/reviews/data=!4m6!14m5!1m4!2m3!1sChZDSUhNMG9nS0VJQ0FnSURNLVptY1FnEAE!2m1!1s0x3f8dfd6554ae6111:0xba867031ff57b33",
            "name": "places/ChIJEWGuVGX9jT8RM3v1HwNnqAs/reviews/ChZDSUhNMG9nS0VJQ0FnSURNLVptY1FnEAE",
            "originalText": {
                "languageCode": "en",
                "text": "We booked this restaurant for the lunch and they said we don't have lunch, its dinner only!! How on earth a restaurant doesn't provide lunch?! Even if it doesn't, you should make it clear during booking!!!"
            },
            "publishTime": "2020-01-05T08:26:52.197646Z",
            "rating": 1,
            "relativePublishTimeDescription": "5 years ago",
            "text": {
                "languageCode": "en",
                "text": "We booked this restaurant for the lunch and they said we don't have lunch, its dinner only!! How on earth a restaurant doesn't provide lunch?! Even if it doesn't, you should make it clear during booking!!!"
            }
        },
        {
            "authorAttribution": {
                "displayName": "Dr.HR Salehi",
                "photoUri": "https://lh3.googleusercontent.com/a-/ALV-UjWcsjmEOb5t8_cKMpFGON2Z4x8uQIvsOhsC9dx9mbi568DswtMs=s128-c0x00000000-cc-rp-mo",
                "uri": "https://www.google.com/maps/contrib/112307854462996255931/reviews"
            },
            "flagContentUri": "https://www.google.com/local/review/rap/report?postId=ChdDSUhNMG9nS0VJQ0FnSUNVLU16c3NnRRAB&d=17924085&t=1",
            "googleMapsUri": "https://www.google.com/maps/reviews/data=!4m6!14m5!1m4!2m3!1sChdDSUhNMG9nS0VJQ0FnSUNVLU16c3NnRRAB!2m1!1s0x3f8dfd6554ae6111:0xba867031ff57b33",
            "name": "places/ChIJEWGuVGX9jT8RM3v1HwNnqAs/reviews/ChdDSUhNMG9nS0VJQ0FnSUNVLU16c3NnRRAB",
            "originalText": {
                "languageCode": "en",
                "text": "Good restaurant. Tidy and on time. Quality are acceptable."
            },
            "publishTime": "2019-07-17T09:19:33.575454Z",
            "rating": 4,
            "relativePublishTimeDescription": "6 years ago",
            "text": {
                "languageCode": "en",
                "text": "Good restaurant. Tidy and on time. Quality are acceptable."
            }
        },
        {
            "authorAttribution": {
                "displayName": "Iman Sor",
                "photoUri": "https://lh3.googleusercontent.com/a/ACg8ocImqQjHhDTTxSoulFx2UPRxTMz-utmW1vVBa7tJY9TGhB_ulg=s128-c0x00000000-cc-rp-mo",
                "uri": "https://www.google.com/maps/contrib/115414305950544521645/reviews"
            },
            "flagContentUri": "https://www.google.com/local/review/rap/report?postId=ChZDSUhNMG9nS0VJQ0FnSURzd0xxcFN3EAE&d=17924085&t=1",
            "googleMapsUri": "https://www.google.com/maps/reviews/data=!4m6!14m5!1m4!2m3!1sChZDSUhNMG9nS0VJQ0FnSURzd0xxcFN3EAE!2m1!1s0x3f8dfd6554ae6111:0xba867031ff57b33",
            "name": "places/ChIJEWGuVGX9jT8RM3v1HwNnqAs/reviews/ChZDSUhNMG9nS0VJQ0FnSURzd0xxcFN3EAE",
            "originalText": {
                "languageCode": "en",
                "text": "It is beautiful"
            },
            "publishTime": "2020-02-20T07:49:15.441403Z",
            "rating": 3,
            "relativePublishTimeDescription": "5 years ago",
            "text": {
                "languageCode": "en",
                "text": "It is beautiful"
            }
        }
    ],
    "shortFormattedAddress": "Tehran، استان تهران، تهران، فلکه دوم صادقیه،خیابان ایت ا..کاشانی،جنب، خیابان مهران،، P8GC+WJC",
    "timeZone": {
        "id": "Asia/Tehran"
    },
    "types": [
        "restaurant",
        "food",
        "point_of_interest",
        "establishment"
    ],
    "userRatingCount": 67,
    "utcOffsetMinutes": 210,
    "viewport": {
        "high": {
            "latitude": 35.7285673802915,
            "longitude": 51.32281028029149
        },
        "low": {
            "latitude": 35.7258694197085,
            "longitude": 51.3201123197085
        }
    },
    "timestamp": 1765104817
}